MANIFEST.in
setup.py
web_linkedin_view.xml
./__init__.py
./__openerp__.py
./web_linkedin.py
i18n/ar.po
i18n/cs.po
i18n/de.po
i18n/es.po
i18n/fr.po
i18n/hr.po
i18n/hu.po
i18n/it.po
i18n/mk.po
i18n/mn.po
i18n/nl.po
i18n/pl.po
i18n/pt.po
i18n/pt_BR.po
i18n/ro.po
i18n/sl.po
i18n/tr.po
i18n/web_linkedin.pot
i18n/zh_CN.po
openerp_web_linkedin.egg-info/PKG-INFO
openerp_web_linkedin.egg-info/SOURCES.txt
openerp_web_linkedin.egg-info/dependency_links.txt
openerp_web_linkedin.egg-info/requires.txt
openerp_web_linkedin.egg-info/top_level.txt
static/src/img/Linkedin_blue.png
static/src/img/ghost_profile_60x60_v1.png
static/src/js/linkedin.js
static/src/xml/linkedin.xml